hcdel/Eula.txt
hcdel/README.MD
hcdel/__init__.py
hcdel/hcdel.cmd
hcdel/hcdel.py
hcdel/movefile.exe
hcdel/movefile64.exe
hcdel/movefile64a.exe
hcdel/pendmoves.exe
hcdel/pendmoves64.exe
hcdel/pendmoves64a.exe
hcdel/requirements.txt
hcdel/thirdparty.json
hcdel-0.10.dist-info/LICENSE.rst
hcdel-0.10.dist-info/METADATA
hcdel-0.10.dist-info/WHEEL
hcdel-0.10.dist-info/top_level.txt
hcdel-0.10.dist-info/RECORD
