Metadata-Version: 2.1
Name: hcdel
Version: 0.10
Summary: Deletes files (hardcore mode - Windows only)
Home-page: https://github.com/hansalemaos/hcdel
Author: Johannes Fischer
Author-email: aulasparticularesdealemaosp@gmail.com
License: MIT
Keywords: pendmoves,delete,files
Classifier: Development Status :: 4 - Beta
Classifier: Programming Language :: Python :: 3 :: Only
Classifier: Programming Language :: Python :: 3.10
Classifier: Topic :: Software Development :: Libraries :: Python Modules
Classifier: Topic :: Utilities
License-File: LICENSE.rst
Requires-Dist: escape-windows-filepath
Requires-Dist: getfilenuitkapython
Requires-Dist: hackyargparser
Requires-Dist: list-all-files-recursively
